nestedfunctions/VERSION
nestedfunctions/__init__.py
nestedfunctions/version.py
nestedfunctions/functions/__init__.py
nestedfunctions/functions/add_nested_field.py
nestedfunctions/functions/binary_generalization.py
nestedfunctions/functions/date_format.py
nestedfunctions/functions/drop.py
nestedfunctions/functions/duplicate.py
nestedfunctions/functions/expr.py
nestedfunctions/functions/field_rename.py
nestedfunctions/functions/fillna.py
nestedfunctions/functions/filter.py
nestedfunctions/functions/hash.py
nestedfunctions/functions/nullify.py
nestedfunctions/functions/redact.py
nestedfunctions/functions/str_concat.py
nestedfunctions/functions/str_regx_extract.py
nestedfunctions/functions/terminal_operations.py
nestedfunctions/functions/truncate.py
nestedfunctions/functions/whitelist.py
nestedfunctions/processors/__init__.py
nestedfunctions/processors/add_operation_processor.py
nestedfunctions/processors/any_level_processor.py
nestedfunctions/processors/coreprocessor.py
nestedfunctions/processors/terminal_operation_processor.py
nestedfunctions/processors/terminal_operation_processor_with_predicate.py
nestedfunctions/spark_schema/__init__.py
nestedfunctions/spark_schema/schema_flattener.py
nestedfunctions/spark_schema/utility.py
nestedfunctions/utils/__init__.py
nestedfunctions/utils/iterators/__init__.py
nestedfunctions/utils/iterators/iterator_utils.py
nestedfunctions/validation/__init__.py
nestedfunctions/validation/validators.py
pyspark_nested_functions-0.1.7.dist-info/LICENSE
pyspark_nested_functions-0.1.7.dist-info/METADATA
pyspark_nested_functions-0.1.7.dist-info/WHEEL
pyspark_nested_functions-0.1.7.dist-info/top_level.txt
pyspark_nested_functions-0.1.7.dist-info/RECORD
