Metadata-Version: 2.1
Name: pyspark_nested_functions
Version: 0.1.7
Summary: Utility functions to manipulate nested structures using pyspark
Home-page: https://github.com/golosegor/pyspark-nested-fields-functions
Author: Brend Braeckmans <brend@distilleddata.be>, Egor Goloshchapov <golosegor@gmail.com>
Classifier: Programming Language :: Python :: 3
Classifier: Programming Language :: Python :: 3.7
Classifier: Programming Language :: Python :: 3.8
Classifier: Programming Language :: Python :: 3.9
Classifier: Programming Language :: Python :: 3.10
Classifier: Programming Language :: Python :: 3.11
Requires-Python: >=3.7, <3.12
License-File: LICENSE
